LICENSE.md
MANIFEST.in
README.md
setup.cfg
setup.py
maeham1.egg-info/PKG-INFO
maeham1.egg-info/SOURCES.txt
maeham1.egg-info/dependency_links.txt
maeham1.egg-info/entry_points.txt
maeham1.egg-info/requires.txt
maeham1.egg-info/top_level.txt
maepagesplugin/__init__.py
maepagesplugin/arrange.py
maepagesplugin/meta.py
maepagesplugin/navigation.py
maepagesplugin/options.py
maepagesplugin/plugin.py
maepagesplugin/utils.py